{
    "galleries": [
        {
            "title": "22.07.2017 Sommerfest Academia",
            "date": "22.07.2017", 
            "images": [
                {
                    "src": "assets/2017-07-22/_MG_8502.webp",
                    "alt": "Sommerfest Academia"
                },
                {
                    "src": "assets/2017-07-22/_MG_8510.webp",
                    "alt": "Sommerfest Academia"
                },
                {
                    "src": "assets/2017-07-22/_MG_8511.webp",
                    "alt": "Sommerfest Academia"
                },
                {
                    "src": "assets/2017-07-22/_MG_8512.webp",
                    "alt": "Sommerfest Academia"
                },
                {
                    "src": "assets/2017-07-22/_MG_8513.webp",
                    "alt": "Sommerfest Academia"
                },
                {
                    "src": "assets/2017-07-22/_MG_8514.webp",
                    "alt": "Sommerfest Academia"
                },
                {
                    "src": "assets/2017-07-22/_MG_8515.webp",
                    "alt": "Sommerfest Academia"
                },
                {
                    "src": "assets/2017-07-22/_MG_8516.webp",
                    "alt": "Sommerfest Academia"
                },
                {
                    "src": "assets/2017-07-22/_MG_8517.webp",
                    "alt": "Sommerfest Academia"
                },
                {
                    "src": "assets/2017-07-22/_MG_8518.webp",
                    "alt": "Sommerfest Academia"
                },
                {
                    "src": "assets/2017-07-22/_MG_8519.webp",
                    "alt": "Sommerfest Academia"
                },
                {
                    "src": "assets/2017-07-22/_MG_8523.webp",
                    "alt": "Sommerfest Academia"
                },
                {
                    "src": "assets/2017-07-22/_MG_8524.webp",
                    "alt": "Sommerfest Academia"
                },
                {
                    "src": "assets/2017-07-22/_MG_8537.webp",
                    "alt": "Sommerfest Academia"
                },
                {
                    "src": "assets/2017-07-22/_MG_8538.webp",
                    "alt": "Sommerfest Academia"
                },
                {
                    "src": "assets/2017-07-22/_MG_8539.webp",
                    "alt": "Sommerfest Academia"
                },
                {
                    "src": "assets/2017-07-22/_MG_8541.webp",
                    "alt": "Sommerfest Academia"
                },
                {
                    "src": "assets/2017-07-22/_MG_8542.webp",
                    "alt": "Sommerfest Academia"
                },
                {
                    "src": "assets/2017-07-22/_MG_8543.webp",
                    "alt": "Sommerfest Academia"
                },
                {
                    "src": "assets/2017-07-22/_MG_8544.webp",
                    "alt": "Sommerfest Academia"
                },
                {
                    "src": "assets/2017-07-22/_MG_8545.webp",
                    "alt": "Sommerfest Academia"
                },
                {
                    "src": "assets/2017-07-22/_MG_8546.webp",
                    "alt": "Sommerfest Academia"
                },
                {
                    "src": "assets/2017-07-22/_MG_8548.webp",
                    "alt": "Sommerfest Academia"
                },
                {
                    "src": "assets/2017-07-22/_MG_8550.webp",
                    "alt": "Sommerfest Academia"
                },
                {
                    "src": "assets/2017-07-22/_MG_8551.webp",
                    "alt": "Sommerfest Academia"
                },
                {
                    "src": "assets/2017-07-22/_MG_8552.webp",
                    "alt": "Sommerfest Academia"
                },
                {
                    "src": "assets/2017-07-22/_MG_8556.webp",
                    "alt": "Sommerfest Academia"
                },
                {
                    "src": "assets/2017-07-22/_MG_8558.webp",
                    "alt": "Sommerfest Academia"
                },
                {
                    "src": "assets/2017-07-22/_MG_8559.webp",
                    "alt": "Sommerfest Academia"
                },
                {
                    "src": "assets/2017-07-22/_MG_8560.webp",
                    "alt": "Sommerfest Academia"
                },
                {
                    "src": "assets/2017-07-22/_MG_8561.webp",
                    "alt": "Sommerfest Academia"
                },
                {
                    "src": "assets/2017-07-22/_MG_8565.webp",
                    "alt": "Sommerfest Academia"
                },
                {
                    "src": "assets/2017-07-22/_MG_8570.webp",
                    "alt": "Sommerfest Academia"
                },
                {
                    "src": "assets/2017-07-22/_MG_8571.webp",
                    "alt": "Sommerfest Academia"
                },
                {
                    "src": "assets/2017-07-22/_MG_8580.webp",
                    "alt": "Sommerfest Academia"
                },
                {
                    "src": "assets/2017-07-22/_MG_8581.webp",
                    "alt": "Sommerfest Academia"
                },
                {
                    "src": "assets/2017-07-22/_MG_8586.webp",
                    "alt": "Sommerfest Academia"
                },
                {
                    "src": "assets/2017-07-22/_MG_8589.webp",
                    "alt": "Sommerfest Academia"
                },
                {
                    "src": "assets/2017-07-22/_MG_8591.webp",
                    "alt": "Sommerfest Academia"
                },
                {
                    "src": "assets/2017-07-22/_MG_8592.webp",
                    "alt": "Sommerfest Academia"
                },
                {
                    "src": "assets/2017-07-22/_MG_8595.webp",
                    "alt": "Sommerfest Academia"
                },
                {
                    "src": "assets/2017-07-22/_MG_8603.webp",
                    "alt": "Sommerfest Academia"
                },
                {
                    "src": "assets/2017-07-22/_MG_8607.webp",
                    "alt": "Sommerfest Academia"
                },
                {
                    "src": "assets/2017-07-22/_MG_8608.webp",
                    "alt": "Sommerfest Academia"
                },
                {
                    "src": "assets/2017-07-22/_MG_8621.webp",
                    "alt": "Sommerfest Academia"
                },
                {
                    "src": "assets/2017-07-22/_MG_8639.webp",
                    "alt": "Sommerfest Academia"
                },
                {
                    "src": "assets/2017-07-22/_MG_8641.webp",
                    "alt": "Sommerfest Academia"
                },
                {
                    "src": "assets/2017-07-22/_MG_8642.webp",
                    "alt": "Sommerfest Academia"
                },
                {
                    "src": "assets/2017-07-22/_MG_8644.webp",
                    "alt": "Sommerfest Academia"
                },
                {
                    "src": "assets/2017-07-22/_MG_8665.webp",
                    "alt": "Sommerfest Academia"
                },
                {
                    "src": "assets/2017-07-22/_MG_8679.webp",
                    "alt": "Sommerfest Academia"
                }
            ]
        },
        {
            "title": "23.07.2017 Gruppenfotos",
            "date": "23.07.2017", 
            "images": [
                {
                    "src": "assets/2017-07-23/_MG_8703.webp",
                    "alt": "Gruppenfoto Academia"
                },
                {
                    "src": "assets/2017-07-23/_MG_8689.webp",
                    "alt": "Gruppenfoto Academia"
                },
                {
                    "src": "assets/2017-07-23/_MG_8717.webp",
                    "alt": "Gruppenfoto Academia"
                },
                {
                    "src": "assets/2017-07-23/_MG_8726.webp",
                    "alt": "Gruppenfoto Academia"
                },
                {
                    "src": "assets/2017-07-23/_MG_8727.webp",
                    "alt": "Gruppenfoto Academia"
                },
                {
                    "src": "assets/2017-07-23/_MG_8728.webp",
                    "alt": "Gruppenfoto Academia"
                },
                {
                    "src": "assets/2017-07-23/_MG_8729.webp",
                    "alt": "Gruppenfoto Academia"
                },
                {
                    "src": "assets/2017-07-23/_MG_8730.webp",
                    "alt": "Gruppenfoto Academia"
                },
                {
                    "src": "assets/2017-07-23/_MG_8731.webp",
                    "alt": "Gruppenfoto Academia"
                },
                {
                    "src": "assets/2017-07-23/_MG_8734.webp",
                    "alt": "Gruppenfoto Academia"
                },
                {
                    "src": "assets/2017-07-23/_MG_8735.webp",
                    "alt": "Gruppenfoto Academia"
                },
                {
                    "src": "assets/2017-07-23/_MG_8738.webp",
                    "alt": "Gruppenfoto Academia"
                },
                {
                    "src": "assets/2017-07-23/_MG_8740.webp",
                    "alt": "Gruppenfoto Academia"
                },
                {
                    "src": "assets/2017-07-23/_MG_8754.webp",
                    "alt": "Gruppenfoto Academia"
                },
                {
                    "src": "assets/2017-07-23/_MG_8755.webp",
                    "alt": "Gruppenfoto Academia"
                },
                {
                    "src": "assets/2017-07-23/_MG_8758.webp",
                    "alt": "Gruppenfoto Academia"
                },
                {
                    "src": "assets/2017-07-23/_MG_8766.webp",
                    "alt": "Gruppenfoto Academia"
                },
                {
                    "src": "assets/2017-07-23/_MG_8770.webp",
                    "alt": "Gruppenfoto Academia"
                },
                {
                    "src": "assets/2017-07-23/_MG_8771.webp",
                    "alt": "Gruppenfoto Academia"
                },
                {
                    "src": "assets/2017-07-23/_MG_8774.webp",
                    "alt": "Gruppenfoto Academia"
                },
                {
                    "src": "assets/2017-07-23/_MG_8776.webp",
                    "alt": "Gruppenfoto Academia"
                },
                {
                    "src": "assets/2017-07-23/_MG_8784.webp",
                    "alt": "Gruppenfoto Academia"
                },
                {
                    "src": "assets/2017-07-23/_MG_8785.webp",
                    "alt": "Gruppenfoto Academia"
                },
                {
                    "src": "assets/2017-07-23/_MG_8787.webp",
                    "alt": "Gruppenfoto Academia"
                },
                {
                    "src": "assets/2017-07-23/_MG_8789.webp",
                    "alt": "Gruppenfoto Academia"
                },
                {
                    "src": "assets/2017-07-23/_MG_8790.webp",
                    "alt": "Gruppenfoto Academia"
                },
                {
                    "src": "assets/2017-07-23/_MG_8791.webp",
                    "alt": "Gruppenfoto Academia"
                },
                {
                    "src": "assets/2017-07-23/_MG_8792.webp",
                    "alt": "Gruppenfoto Academia"
                },
                {
                    "src": "assets/2017-07-23/_MG_8795.webp",
                    "alt": "Gruppenfoto Academia"
                },
                {
                    "src": "assets/2017-07-23/_MG_8796.webp",
                    "alt": "Gruppenfoto Academia"
                },
                {
                    "src": "assets/2017-07-23/_MG_8799.webp",
                    "alt": "Gruppenfoto Academia"
                },
                {
                    "src": "assets/2017-07-23/_MG_8805.webp",
                    "alt": "Gruppenfoto Academia"
                },
                {
                    "src": "assets/2017-07-23/_MG_8817.webp",
                    "alt": "Gruppenfoto Academia"
                }
            ]
        }
    ]
}
